{
    "eating disorder": [
        "depression",
        "anxiety and nervousness",
        "depressive or psychotic symptoms",
        "decreased appetite",
        "abusing alcohol",
        "excessive appetite",
        "difficulty eating",
        "weight gain",
        "excessive anger",
        "insomnia",
        "vomiting blood",
        "acne or pimples"
    ],
    "chronic pain disorder": [
        "back pain",
        "low back pain",
        "ache all over",
        "leg pain",
        "neck pain",
        "headache",
        "sharp abdominal pain",
        "shoulder pain",
        "knee pain",
        "hip pain",
        "pelvic pain",
        "lower body pain"
    ],
    "diabetic retinopathy": [
        "diminished vision",
        "spots or clouds in vision",
        "pain in eye",
        "lacrimation",
        "symptoms of eye",
        "eye redness",
        "foreign body sensation in eye",
        "itchiness of eye",
        "blindness",
        "bleeding from eye",
        "abnormal movement of eyelid",
        "double vision"
    ],
    "fibromyalgia": [
        "back pain",
        "ache all over",
        "neck pain",
        "muscle pain",
        "leg pain",
        "headache",
        "shoulder pain",
        "low back pain",
        "sharp chest pain",
        "arm pain",
        "hip pain",
        "fatigue"
    ],
    "chalazion": [
        "mass on eyelid",
        "pain in eye",
        "swollen eye",
        "eye redness",
        "symptoms of eye",
        "eyelid swelling",
        "eyelid lesion or rash",
        "diminished vision",
        "itchiness of eye",
        "skin growth",
        "foreign body sensation in eye",
        "lacrimation"
    ],
    "corneal disorder": [
        "diminished vision",
        "pain in eye",
        "eye redness",
        "spots or clouds in vision",
        "symptoms of eye",
        "foreign body sensation in eye",
        "lacrimation",
        "itchiness of eye",
        "white discharge from eye",
        "swollen eye",
        "double vision",
        "eyelid lesion or rash"
    ],
    "endophthalmitis": [
        "pain in eye",
        "eye redness",
        "swollen eye",
        "diminished vision",
        "itchiness of eye",
        "mass on eyelid",
        "paresthesia",
        "painful sinuses",
        "skin lesion",
        "foot or toe pain",
        "lacrimation",
        "painful urination"
    ]
}
